{
  "daily_pnl": -2.028915,
  "daily_trades": 1,
  "total_trades": 2,
  "winning_trades": 1,
  "losing_trades": 1,
  "consecutive_losses": 1,
  "paused_until": "",
  "last_trade_time": "2026-02-09T18:44:34.139238",
  "last_reset_date": "2026-02-09",
  "trade_log": [
    {
      "time": "2026-02-09T04:54:49.211542",
      "side": "LONG",
      "entry": 70951.0,
      "pnl": 0.42,
      "exit_reason": "TIME_EXIT (held 7.8h, +0.54%)",
      "confidence": 75,
      "trend_score": 55.0
    },
    {
      "time": "2026-02-09T18:44:34.139472",
      "side": "SHORT",
      "entry": 69030.0,
      "pnl": -2.03,
      "exit_reason": "STOP_LOSS",
      "confidence": 70,
      "trend_score": -54.0
    }
  ]
}